Metadata-Version: 2.1
Name: git-annex-metadata-edit
Version: 1.0.0
Summary: Edit git-annex metadata in your $EDITOR
Home-page: https://gitlab.com/nobodyinperson/git-annex-metadata-edit
Author: Yann Buechau
Author-email: nobodyinperson@posteo.de
License: GPLv3
Keywords: git-annex,git
Classifier: License :: OSI Approved :: GNU General Public License v3 (GPLv3)
Requires-Python: >=3.6
License-File: LICENSE
